<?xml version="1.0" ?>
<annotation>
	<folder>text</folder>
	<filename>img_3116.jpg</filename>
	<source>
		<database>coco_text_database</database>
		<annotation>text</annotation>
		<image>text</image>
		<flickrid>000000</flickrid>
	</source>
	<owner>
		<name>ms</name>
	</owner>
	<size>
		<width>1010</width>
		<height>676</height>
		<depth>3</depth>
	</size>
	<segmented>0</segmented>
	<object>
		<name>text</name>
		<pose>none</pose>
		<truncated>0</truncated>
		<difficult>0</difficult>
		<bndbox>
			<xmin>558</xmin>
			<ymin>380</ymin>
			<xmax>573</xmax>
			<ymax>402</ymax>
		</bndbox>
	</object>
	<object>
		<name>text</name>
		<pose>none</pose>
		<truncated>0</truncated>
		<difficult>0</difficult>
		<bndbox>
			<xmin>574</xmin>
			<ymin>380</ymin>
			<xmax>589</xmax>
			<ymax>402</ymax>
		</bndbox>
	</object>
	<object>
		<name>text</name>
		<pose>none</pose>
		<truncated>0</truncated>
		<difficult>0</difficult>
		<bndbox>
			<xmin>590</xmin>
			<ymin>380</ymin>
			<xmax>605</xmax>
			<ymax>402</ymax>
		</bndbox>
	</object>
	<object>
		<name>text</name>
		<pose>none</pose>
		<truncated>0</truncated>
		<difficult>0</difficult>
		<bndbox>
			<xmin>606</xmin>
			<ymin>380</ymin>
			<xmax>621</xmax>
			<ymax>402</ymax>
		</bndbox>
	</object>
	<object>
		<name>text</name>
		<pose>none</pose>
		<truncated>0</truncated>
		<difficult>0</difficult>
		<bndbox>
			<xmin>622</xmin>
			<ymin>380</ymin>
			<xmax>637</xmax>
			<ymax>402</ymax>
		</bndbox>
	</object>
	<object>
		<name>text</name>
		<pose>none</pose>
		<truncated>0</truncated>
		<difficult>0</difficult>
		<bndbox>
			<xmin>638</xmin>
			<ymin>380</ymin>
			<xmax>653</xmax>
			<ymax>402</ymax>
		</bndbox>
	</object>
	<object>
		<name>text</name>
		<pose>none</pose>
		<truncated>0</truncated>
		<difficult>0</difficult>
		<bndbox>
			<xmin>654</xmin>
			<ymin>380</ymin>
			<xmax>669</xmax>
			<ymax>402</ymax>
		</bndbox>
	</object>
	<object>
		<name>text</name>
		<pose>none</pose>
		<truncated>0</truncated>
		<difficult>0</difficult>
		<bndbox>
			<xmin>670</xmin>
			<ymin>380</ymin>
			<xmax>685</xmax>
			<ymax>402</ymax>
		</bndbox>
	</object>
	<object>
		<name>text</name>
		<pose>none</pose>
		<truncated>0</truncated>
		<difficult>0</difficult>
		<bndbox>
			<xmin>686</xmin>
			<ymin>380</ymin>
			<xmax>701</xmax>
			<ymax>402</ymax>
		</bndbox>
	</object>
	<object>
		<name>text</name>
		<pose>none</pose>
		<truncated>0</truncated>
		<difficult>0</difficult>
		<bndbox>
			<xmin>702</xmin>
			<ymin>380</ymin>
			<xmax>717</xmax>
			<ymax>402</ymax>
		</bndbox>
	</object>
	<object>
		<name>text</name>
		<pose>none</pose>
		<truncated>0</truncated>
		<difficult>0</difficult>
		<bndbox>
			<xmin>718</xmin>
			<ymin>380</ymin>
			<xmax>733</xmax>
			<ymax>402</ymax>
		</bndbox>
	</object>
	<object>
		<name>text</name>
		<pose>none</pose>
		<truncated>0</truncated>
		<difficult>0</difficult>
		<bndbox>
			<xmin>734</xmin>
			<ymin>380</ymin>
			<xmax>749</xmax>
			<ymax>402</ymax>
		</bndbox>
	</object>
	<object>
		<name>text</name>
		<pose>none</pose>
		<truncated>0</truncated>
		<difficult>0</difficult>
		<bndbox>
			<xmin>750</xmin>
			<ymin>380</ymin>
			<xmax>765</xmax>
			<ymax>402</ymax>
		</bndbox>
	</object>
	<object>
		<name>text</name>
		<pose>none</pose>
		<truncated>0</truncated>
		<difficult>0</difficult>
		<bndbox>
			<xmin>766</xmin>
			<ymin>380</ymin>
			<xmax>781</xmax>
			<ymax>402</ymax>
		</bndbox>
	</object>
	<object>
		<name>text</name>
		<pose>none</pose>
		<truncated>0</truncated>
		<difficult>0</difficult>
		<bndbox>
			<xmin>782</xmin>
			<ymin>380</ymin>
			<xmax>797</xmax>
			<ymax>402</ymax>
		</bndbox>
	</object>
	<object>
		<name>text</name>
		<pose>none</pose>
		<truncated>0</truncated>
		<difficult>0</difficult>
		<bndbox>
			<xmin>798</xmin>
			<ymin>380</ymin>
			<xmax>813</xmax>
			<ymax>402</ymax>
		</bndbox>
	</object>
	<object>
		<name>text</name>
		<pose>none</pose>
		<truncated>0</truncated>
		<difficult>0</difficult>
		<bndbox>
			<xmin>814</xmin>
			<ymin>380</ymin>
			<xmax>829</xmax>
			<ymax>402</ymax>
		</bndbox>
	</object>
	<object>
		<name>text</name>
		<pose>none</pose>
		<truncated>0</truncated>
		<difficult>0</difficult>
		<bndbox>
			<xmin>830</xmin>
			<ymin>380</ymin>
			<xmax>845</xmax>
			<ymax>402</ymax>
		</bndbox>
	</object>
	<object>
		<name>text</name>
		<pose>none</pose>
		<truncated>0</truncated>
		<difficult>0</difficult>
		<bndbox>
			<xmin>846</xmin>
			<ymin>380</ymin>
			<xmax>861</xmax>
			<ymax>402</ymax>
		</bndbox>
	</object>
	<object>
		<name>text</name>
		<pose>none</pose>
		<truncated>0</truncated>
		<difficult>0</difficult>
		<bndbox>
			<xmin>862</xmin>
			<ymin>380</ymin>
			<xmax>877</xmax>
			<ymax>402</ymax>
		</bndbox>
	</object>
	<object>
		<name>text</name>
		<pose>none</pose>
		<truncated>0</truncated>
		<difficult>0</difficult>
		<bndbox>
			<xmin>878</xmin>
			<ymin>380</ymin>
			<xmax>893</xmax>
			<ymax>402</ymax>
		</bndbox>
	</object>
	<object>
		<name>text</name>
		<pose>none</pose>
		<truncated>0</truncated>
		<difficult>0</difficult>
		<bndbox>
			<xmin>147</xmin>
			<ymin>443</ymin>
			<xmax>162</xmax>
			<ymax>576</ymax>
		</bndbox>
	</object>
	<object>
		<name>text</name>
		<pose>none</pose>
		<truncated>0</truncated>
		<difficult>0</difficult>
		<bndbox>
			<xmin>163</xmin>
			<ymin>443</ymin>
			<xmax>178</xmax>
			<ymax>576</ymax>
		</bndbox>
	</object>
	<object>
		<name>text</name>
		<pose>none</pose>
		<truncated>0</truncated>
		<difficult>0</difficult>
		<bndbox>
			<xmin>179</xmin>
			<ymin>443</ymin>
			<xmax>194</xmax>
			<ymax>576</ymax>
		</bndbox>
	</object>
	<object>
		<name>text</name>
		<pose>none</pose>
		<truncated>0</truncated>
		<difficult>0</difficult>
		<bndbox>
			<xmin>195</xmin>
			<ymin>443</ymin>
			<xmax>210</xmax>
			<ymax>576</ymax>
		</bndbox>
	</object>
	<object>
		<name>text</name>
		<pose>none</pose>
		<truncated>0</truncated>
		<difficult>0</difficult>
		<bndbox>
			<xmin>211</xmin>
			<ymin>443</ymin>
			<xmax>226</xmax>
			<ymax>576</ymax>
		</bndbox>
	</object>
	<object>
		<name>text</name>
		<pose>none</pose>
		<truncated>0</truncated>
		<difficult>0</difficult>
		<bndbox>
			<xmin>227</xmin>
			<ymin>443</ymin>
			<xmax>242</xmax>
			<ymax>576</ymax>
		</bndbox>
	</object>
	<object>
		<name>text</name>
		<pose>none</pose>
		<truncated>0</truncated>
		<difficult>0</difficult>
		<bndbox>
			<xmin>243</xmin>
			<ymin>443</ymin>
			<xmax>258</xmax>
			<ymax>576</ymax>
		</bndbox>
	</object>
	<object>
		<name>text</name>
		<pose>none</pose>
		<truncated>0</truncated>
		<difficult>0</difficult>
		<bndbox>
			<xmin>259</xmin>
			<ymin>443</ymin>
			<xmax>274</xmax>
			<ymax>576</ymax>
		</bndbox>
	</object>
	<object>
		<name>text</name>
		<pose>none</pose>
		<truncated>0</truncated>
		<difficult>0</difficult>
		<bndbox>
			<xmin>275</xmin>
			<ymin>443</ymin>
			<xmax>290</xmax>
			<ymax>576</ymax>
		</bndbox>
	</object>
	<object>
		<name>text</name>
		<pose>none</pose>
		<truncated>0</truncated>
		<difficult>0</difficult>
		<bndbox>
			<xmin>291</xmin>
			<ymin>443</ymin>
			<xmax>306</xmax>
			<ymax>576</ymax>
		</bndbox>
	</object>
	<object>
		<name>text</name>
		<pose>none</pose>
		<truncated>0</truncated>
		<difficult>0</difficult>
		<bndbox>
			<xmin>307</xmin>
			<ymin>443</ymin>
			<xmax>322</xmax>
			<ymax>576</ymax>
		</bndbox>
	</object>
	<object>
		<name>text</name>
		<pose>none</pose>
		<truncated>0</truncated>
		<difficult>0</difficult>
		<bndbox>
			<xmin>323</xmin>
			<ymin>443</ymin>
			<xmax>338</xmax>
			<ymax>576</ymax>
		</bndbox>
	</object>
	<object>
		<name>text</name>
		<pose>none</pose>
		<truncated>0</truncated>
		<difficult>0</difficult>
		<bndbox>
			<xmin>339</xmin>
			<ymin>443</ymin>
			<xmax>354</xmax>
			<ymax>576</ymax>
		</bndbox>
	</object>
	<object>
		<name>text</name>
		<pose>none</pose>
		<truncated>0</truncated>
		<difficult>0</difficult>
		<bndbox>
			<xmin>355</xmin>
			<ymin>443</ymin>
			<xmax>370</xmax>
			<ymax>576</ymax>
		</bndbox>
	</object>
	<object>
		<name>text</name>
		<pose>none</pose>
		<truncated>0</truncated>
		<difficult>0</difficult>
		<bndbox>
			<xmin>371</xmin>
			<ymin>443</ymin>
			<xmax>386</xmax>
			<ymax>576</ymax>
		</bndbox>
	</object>
	<object>
		<name>text</name>
		<pose>none</pose>
		<truncated>0</truncated>
		<difficult>0</difficult>
		<bndbox>
			<xmin>387</xmin>
			<ymin>443</ymin>
			<xmax>402</xmax>
			<ymax>576</ymax>
		</bndbox>
	</object>
	<object>
		<name>text</name>
		<pose>none</pose>
		<truncated>0</truncated>
		<difficult>0</difficult>
		<bndbox>
			<xmin>403</xmin>
			<ymin>443</ymin>
			<xmax>418</xmax>
			<ymax>576</ymax>
		</bndbox>
	</object>
	<object>
		<name>text</name>
		<pose>none</pose>
		<truncated>0</truncated>
		<difficult>0</difficult>
		<bndbox>
			<xmin>419</xmin>
			<ymin>443</ymin>
			<xmax>434</xmax>
			<ymax>576</ymax>
		</bndbox>
	</object>
	<object>
		<name>text</name>
		<pose>none</pose>
		<truncated>0</truncated>
		<difficult>0</difficult>
		<bndbox>
			<xmin>435</xmin>
			<ymin>443</ymin>
			<xmax>450</xmax>
			<ymax>576</ymax>
		</bndbox>
	</object>
	<object>
		<name>text</name>
		<pose>none</pose>
		<truncated>0</truncated>
		<difficult>0</difficult>
		<bndbox>
			<xmin>451</xmin>
			<ymin>443</ymin>
			<xmax>466</xmax>
			<ymax>576</ymax>
		</bndbox>
	</object>
	<object>
		<name>text</name>
		<pose>none</pose>
		<truncated>0</truncated>
		<difficult>0</difficult>
		<bndbox>
			<xmin>467</xmin>
			<ymin>443</ymin>
			<xmax>482</xmax>
			<ymax>576</ymax>
		</bndbox>
	</object>
	<object>
		<name>text</name>
		<pose>none</pose>
		<truncated>0</truncated>
		<difficult>0</difficult>
		<bndbox>
			<xmin>483</xmin>
			<ymin>443</ymin>
			<xmax>498</xmax>
			<ymax>576</ymax>
		</bndbox>
	</object>
	<object>
		<name>text</name>
		<pose>none</pose>
		<truncated>0</truncated>
		<difficult>0</difficult>
		<bndbox>
			<xmin>499</xmin>
			<ymin>443</ymin>
			<xmax>514</xmax>
			<ymax>576</ymax>
		</bndbox>
	</object>
	<object>
		<name>text</name>
		<pose>none</pose>
		<truncated>0</truncated>
		<difficult>0</difficult>
		<bndbox>
			<xmin>515</xmin>
			<ymin>443</ymin>
			<xmax>530</xmax>
			<ymax>576</ymax>
		</bndbox>
	</object>
	<object>
		<name>text</name>
		<pose>none</pose>
		<truncated>0</truncated>
		<difficult>0</difficult>
		<bndbox>
			<xmin>531</xmin>
			<ymin>443</ymin>
			<xmax>546</xmax>
			<ymax>576</ymax>
		</bndbox>
	</object>
	<object>
		<name>text</name>
		<pose>none</pose>
		<truncated>0</truncated>
		<difficult>0</difficult>
		<bndbox>
			<xmin>547</xmin>
			<ymin>443</ymin>
			<xmax>562</xmax>
			<ymax>576</ymax>
		</bndbox>
	</object>
	<object>
		<name>text</name>
		<pose>none</pose>
		<truncated>0</truncated>
		<difficult>0</difficult>
		<bndbox>
			<xmin>563</xmin>
			<ymin>443</ymin>
			<xmax>578</xmax>
			<ymax>576</ymax>
		</bndbox>
	</object>
	<object>
		<name>text</name>
		<pose>none</pose>
		<truncated>0</truncated>
		<difficult>0</difficult>
		<bndbox>
			<xmin>579</xmin>
			<ymin>443</ymin>
			<xmax>594</xmax>
			<ymax>576</ymax>
		</bndbox>
	</object>
	<object>
		<name>text</name>
		<pose>none</pose>
		<truncated>0</truncated>
		<difficult>0</difficult>
		<bndbox>
			<xmin>595</xmin>
			<ymin>443</ymin>
			<xmax>610</xmax>
			<ymax>576</ymax>
		</bndbox>
	</object>
	<object>
		<name>text</name>
		<pose>none</pose>
		<truncated>0</truncated>
		<difficult>0</difficult>
		<bndbox>
			<xmin>611</xmin>
			<ymin>443</ymin>
			<xmax>626</xmax>
			<ymax>576</ymax>
		</bndbox>
	</object>
	<object>
		<name>text</name>
		<pose>none</pose>
		<truncated>0</truncated>
		<difficult>0</difficult>
		<bndbox>
			<xmin>627</xmin>
			<ymin>443</ymin>
			<xmax>642</xmax>
			<ymax>576</ymax>
		</bndbox>
	</object>
	<object>
		<name>text</name>
		<pose>none</pose>
		<truncated>0</truncated>
		<difficult>0</difficult>
		<bndbox>
			<xmin>643</xmin>
			<ymin>443</ymin>
			<xmax>658</xmax>
			<ymax>576</ymax>
		</bndbox>
	</object>
	<object>
		<name>text</name>
		<pose>none</pose>
		<truncated>0</truncated>
		<difficult>0</difficult>
		<bndbox>
			<xmin>659</xmin>
			<ymin>443</ymin>
			<xmax>674</xmax>
			<ymax>576</ymax>
		</bndbox>
	</object>
	<object>
		<name>text</name>
		<pose>none</pose>
		<truncated>0</truncated>
		<difficult>0</difficult>
		<bndbox>
			<xmin>675</xmin>
			<ymin>443</ymin>
			<xmax>690</xmax>
			<ymax>576</ymax>
		</bndbox>
	</object>
	<object>
		<name>text</name>
		<pose>none</pose>
		<truncated>0</truncated>
		<difficult>0</difficult>
		<bndbox>
			<xmin>691</xmin>
			<ymin>443</ymin>
			<xmax>706</xmax>
			<ymax>576</ymax>
		</bndbox>
	</object>
	<object>
		<name>text</name>
		<pose>none</pose>
		<truncated>0</truncated>
		<difficult>0</difficult>
		<bndbox>
			<xmin>707</xmin>
			<ymin>443</ymin>
			<xmax>722</xmax>
			<ymax>576</ymax>
		</bndbox>
	</object>
	<object>
		<name>text</name>
		<pose>none</pose>
		<truncated>0</truncated>
		<difficult>0</difficult>
		<bndbox>
			<xmin>723</xmin>
			<ymin>443</ymin>
			<xmax>738</xmax>
			<ymax>576</ymax>
		</bndbox>
	</object>
	<object>
		<name>text</name>
		<pose>none</pose>
		<truncated>0</truncated>
		<difficult>0</difficult>
		<bndbox>
			<xmin>739</xmin>
			<ymin>443</ymin>
			<xmax>754</xmax>
			<ymax>576</ymax>
		</bndbox>
	</object>
	<object>
		<name>text</name>
		<pose>none</pose>
		<truncated>0</truncated>
		<difficult>0</difficult>
		<bndbox>
			<xmin>755</xmin>
			<ymin>443</ymin>
			<xmax>770</xmax>
			<ymax>576</ymax>
		</bndbox>
	</object>
	<object>
		<name>text</name>
		<pose>none</pose>
		<truncated>0</truncated>
		<difficult>0</difficult>
		<bndbox>
			<xmin>771</xmin>
			<ymin>443</ymin>
			<xmax>786</xmax>
			<ymax>576</ymax>
		</bndbox>
	</object>
	<object>
		<name>text</name>
		<pose>none</pose>
		<truncated>0</truncated>
		<difficult>0</difficult>
		<bndbox>
			<xmin>787</xmin>
			<ymin>443</ymin>
			<xmax>802</xmax>
			<ymax>576</ymax>
		</bndbox>
	</object>
	<object>
		<name>text</name>
		<pose>none</pose>
		<truncated>0</truncated>
		<difficult>0</difficult>
		<bndbox>
			<xmin>803</xmin>
			<ymin>443</ymin>
			<xmax>818</xmax>
			<ymax>576</ymax>
		</bndbox>
	</object>
	<object>
		<name>text</name>
		<pose>none</pose>
		<truncated>0</truncated>
		<difficult>0</difficult>
		<bndbox>
			<xmin>819</xmin>
			<ymin>443</ymin>
			<xmax>834</xmax>
			<ymax>576</ymax>
		</bndbox>
	</object>
	<object>
		<name>text</name>
		<pose>none</pose>
		<truncated>0</truncated>
		<difficult>0</difficult>
		<bndbox>
			<xmin>835</xmin>
			<ymin>443</ymin>
			<xmax>850</xmax>
			<ymax>576</ymax>
		</bndbox>
	</object>
	<object>
		<name>text</name>
		<pose>none</pose>
		<truncated>0</truncated>
		<difficult>0</difficult>
		<bndbox>
			<xmin>851</xmin>
			<ymin>443</ymin>
			<xmax>866</xmax>
			<ymax>576</ymax>
		</bndbox>
	</object>
	<object>
		<name>text</name>
		<pose>none</pose>
		<truncated>0</truncated>
		<difficult>0</difficult>
		<bndbox>
			<xmin>867</xmin>
			<ymin>443</ymin>
			<xmax>882</xmax>
			<ymax>576</ymax>
		</bndbox>
	</object>
	<object>
		<name>text</name>
		<pose>none</pose>
		<truncated>0</truncated>
		<difficult>0</difficult>
		<bndbox>
			<xmin>475</xmin>
			<ymin>257</ymin>
			<xmax>490</xmax>
			<ymax>415</ymax>
		</bndbox>
	</object>
</annotation>
